ca lab5/comparator 2bitt.vhd
library IEEE;
use IEEE.STD_LOGIC_1164.ALL;

entity COMPARATOR_2BIT is
    Port (
        A  : in  STD_LOGIC_VECTOR(1 downto 0);
        B  : in  STD_LOGIC_VECTOR(1 downto 0);
        EQ : out STD_LOGIC;
        GT : out STD_LOGIC;
        LT : out STD_LOGIC
    );
end COMPARATOR_2BIT;

architecture Gate_Level of COMPARATOR_2BIT is

    signal eq1, eq0 : STD_LOGIC;

begin

    -- XNOR using XOR + NOT
    eq1 <= not (A(1) xor B(1));
    eq0 <= not (A(0) xor B(0));

    -- Equality
    EQ <= eq1 and eq0;

    -- Greater Than
    GT <= (A(1) and (not B(1))) or
          (eq1 and A(0) and (not B(0)));

    -- Less Than
    LT <= ((not A(1)) and B(1)) or
          (eq1 and (not A(0)) and B(0));

end Gate_Level;

ca lab5/comparator tbb.vhd
library IEEE;
use IEEE.STD_LOGIC_1164.ALL;

entity COMPARATOR_TB is
end entity COMPARATOR_TB;

architecture Simulation of COMPARATOR_TB is

    signal A, B : STD_LOGIC_VECTOR(1 downto 0);
    signal EQ, GT, LT : STD_LOGIC;

begin

    DUT : entity work.COMPARATOR_2BIT
    port map (
        A  => A,
        B  => B,
        EQ => EQ,
        GT => GT,
        LT => LT
    );

    STIMULUS : process
    begin
        A <= "00"; B <= "00"; wait for 10 ns;
        A <= "00"; B <= "01"; wait for 10 ns;
        A <= "00"; B <= "10"; wait for 10 ns;
        A <= "00"; B <= "11"; wait for 10 ns;

        A <= "01"; B <= "00"; wait for 10 ns;
        A <= "01"; B <= "01"; wait for 10 ns;
        A <= "01"; B <= "10"; wait for 10 ns;
        A <= "01"; B <= "11"; wait for 10 ns;

        A <= "10"; B <= "00"; wait for 10 ns;
        A <= "10"; B <= "01"; wait for 10 ns;
        A <= "10"; B <= "10"; wait for 10 ns;
        A <= "10"; B <= "11"; wait for 10 ns;

        A <= "11"; B <= "00"; wait for 10 ns;
        A <= "11"; B <= "01"; wait for 10 ns;
        A <= "11"; B <= "10"; wait for 10 ns;
        A <= "11"; B <= "11"; wait for 10 ns;

        wait;
    end process;

end architecture Simulation;

ca lab5/comparator.vcd
$date
  Tue Jun 30 10:37:34 2026
$end
$version
  GHDL v0
$end
$timescale
  1 fs
$end
$scope module standard $end
$upscope $end
$scope module std_logic_1164 $end
$upscope $end
$scope module comparator_tb $end
$var reg 2 ! a[1:0] $end
$var reg 2 " b[1:0] $end
$var reg 1 # eq $end
$var reg 1 $ gt $end
$var reg 1 % lt $end
$scope module dut $end
$var reg 2 & a[1:0] $end
$var reg 2 ' b[1:0] $end
$var reg 1 ( eq $end
$var reg 1 ) gt $end
$var reg 1 * lt $end
$var reg 1 + eq1 $end
$var reg 1 , eq0 $end
$upscope $end
$upscope $end
$enddefinitions $end
#0
b00 !
b00 "
1#
0$
0%
b00 &
b00 '
1(
0)
0*
1+
1,
#10000000
b01 "
0#
1%
b01 '
0(
1*
0,
#20000000
b10 "
b10 '
0+
1,
#30000000
b11 "
b11 '
0,
#40000000
b01 !
b00 "
1$
0%
b01 &
b00 '
1)
0*
1+
#50000000
b01 "
1#
0$
b01 '
1(
0)
1,
#60000000
b10 "
0#
0$
1%
b10 '
0(
0)
1*
0+
0,
#70000000
b11 "
b11 '
1,
#80000000
b10 !
b00 "
1$
0%
b10 &
b00 '
1)
0*
#90000000
b01 "
b01 '
0,
#100000000
b10 "
1#
0$
b10 '
1(
0)
1+
1,
#110000000
b11 "
0#
1%
b11 '
0(
1*
0,
#120000000
b11 !
b00 "
1$
0%
b11 &
b00 '
1)
0*
0+
#130000000
b01 "
b01 '
1,
#140000000
b10 "
1$
b10 '
1)
1+
0,
#150000000
b11 "
1#
0$
b11 '
1(
0)
1,
